toy_glacier_project/__init__.py
toy_glacier_project/cli.py
toy_glacier_project/core.py
toy_glacier_project-0.1.0.dist-info/WHEEL
toy_glacier_project-0.1.0.dist-info/entry_points.txt
toy_glacier_project-0.1.0.dist-info/METADATA
toy_glacier_project-0.1.0.dist-info/RECORD
